dm_ollamalib/.gitignore
dm_ollamalib/__init__.py
dm_ollamalib/optionhelper.py
dm_ollamalib/py.typed
dm_ollamalib-0.2.0.dist-info/METADATA
dm_ollamalib-0.2.0.dist-info/WHEEL
dm_ollamalib-0.2.0.dist-info/licenses/LICENSE
dm_ollamalib-0.2.0.dist-info/RECORD
