Metadata-Version: 2.4
Name: dm-ollamalib
Version: 0.2.0
Summary: Functions to parse Ollama options from string and get info on Ollama options.
Project-URL: Homepage, https://github.com/DrMicrobit/dm-ollamalib
Project-URL: GitHub, https://github.com/DrMicrobit/dm-ollamalib
Project-URL: Issues, https://github.com/DrMicrobit/dm-ollamalib/issues
License-Expression: MIT
License-File: LICENSE
Classifier: Development Status :: 5 - Production/Stable
Classifier: Intended Audience :: Developers
Classifier: License :: OSI Approved :: MIT License
Classifier: Operating System :: OS Independent
Classifier: Programming Language :: Python :: 3
Requires-Python: >=3.13
Requires-Dist: ollama>=0.4.8
